phylogeny/__init__.py
phylogeny/core/__init__.py
phylogeny/core/distance.py
phylogeny/core/fpc.py
phylogeny/core/tree.py
phylogeny/models/__init__.py
phylogeny/models/cfn.py
phylogeny/reconstruction/__init__.py
phylogeny/reconstruction/allquartets.py
phylogeny/reconstruction/clocklike.py
phylogeny/reconstruction/clocklike1.py
phylogeny/reconstruction/clocklike2.py
phylogeny/reconstruction/ultrametric.py
phylogeny-0.1.1.dist-info/DESCRIPTION.rst
phylogeny-0.1.1.dist-info/METADATA
phylogeny-0.1.1.dist-info/RECORD
phylogeny-0.1.1.dist-info/WHEEL
phylogeny-0.1.1.dist-info/metadata.json
phylogeny-0.1.1.dist-info/top_level.txt
