Metadata-Version: 2.0
Name: phylogeny
Version: 0.1.1
Summary: An exploration of algorithms for phylogeny reconstruction.
Home-page: https://github.com/Ad115/Phylogeny
Author: Ad115
Author-email: a.garcia230395@gmail.com
License: UNKNOWN
Project-URL: Bug Reports, https://github.com/Ad115/Phylogeny/issues
Project-URL: Say Thanks!, https://saythanks.io/to/Ad115
Project-URL: Source, https://github.com/Ad115/Phylogeny/
Project-URL: Author, https://agargar.wordpress.com/
Keywords: phylogeny reconstruction inference evolution
Platform: UNKNOWN
Classifier: Development Status :: 3 - Alpha
Classifier: Intended Audience :: Science/Research
Classifier: Intended Audience :: Developers
Classifier: Topic :: Scientific/Engineering :: Bio-Informatics
Classifier: Topic :: Scientific/Engineering :: Medical Science Apps.
Classifier: License :: OSI Approved :: MIT License
Classifier: Programming Language :: Python :: 3 :: Only
Provides-Extra: dev
Requires-Dist: ete3
Requires-Dist: matplotlib
Requires-Dist: numpy
Requires-Dist: networkx
Provides-Extra: dev
Requires-Dist: jupyter; extra == 'dev'
Requires-Dist: cellsystem; extra == 'dev'
